pydicer/__init__.py
pydicer/analyse/__init__.py
pydicer/analyse/compare.py
pydicer/analyse/data.py
pydicer/cli/__init__.py
pydicer/cli/contants.py
pydicer/cli/input.py
pydicer/cli/run.py
pydicer/config.py
pydicer/constants.py
pydicer/convert/__init__.py
pydicer/convert/data.py
pydicer/convert/headers.py
pydicer/convert/pt.py
pydicer/convert/rtstruct.py
pydicer/dataset/__init__.py
pydicer/dataset/functions.py
pydicer/dataset/nnunet.py
pydicer/dataset/preparation.py
pydicer/dataset/structureset.py
pydicer/generate/__init__.py
pydicer/generate/mhubconfigs/casust.yml
pydicer/generate/mhubconfigs/lungmask.yml
pydicer/generate/mhubconfigs/nnunet_liver.yml
pydicer/generate/mhubconfigs/nnunet_pancreas.yml
pydicer/generate/mhubconfigs/platipy.yml
pydicer/generate/mhubconfigs/totalsegmentator.yml
pydicer/generate/models.py
pydicer/generate/object.py
pydicer/generate/segmentation.py
pydicer/input/__init__.py
pydicer/input/base.py
pydicer/input/filesystem.py
pydicer/input/orthanc.py
pydicer/input/pacs.py
pydicer/input/tcia.py
pydicer/input/test.py
pydicer/input/web.py
pydicer/logger.py
pydicer/preprocess/__init__.py
pydicer/preprocess/data.py
pydicer/quarantine.py
pydicer/tool.py
pydicer/utils.py
pydicer/visualise/__init__.py
pydicer/visualise/data.py
pydicer-0.2.0.dist-info/LICENSE
pydicer-0.2.0.dist-info/METADATA
pydicer-0.2.0.dist-info/WHEEL
pydicer-0.2.0.dist-info/RECORD
