Metadata-Version: 2.1
Name: pydicer
Version: 0.2.0
Summary: PYthon Dicom Image ConvertER
License: Apache-2.0
Author: Ingham Medical Physics
Requires-Python: >=3.8,<4.0
Classifier: Development Status :: 4 - Beta
Classifier: License :: OSI Approved :: Apache Software License
Classifier: Operating System :: OS Independent
Classifier: Programming Language :: Python :: 3
Classifier: Programming Language :: Python :: 3.8
Classifier: Programming Language :: Python :: 3.9
Classifier: Programming Language :: Python :: 3.10
Classifier: Programming Language :: Python :: 3.11
Classifier: Programming Language :: Python :: 3.12
Classifier: Topic :: Scientific/Engineering :: Image Processing
Classifier: Topic :: Scientific/Engineering :: Medical Science Apps.
Classifier: Topic :: Scientific/Engineering :: Visualization
Requires-Dist: SimpleITK (>=2.0.2)
Requires-Dist: argparse (>=1.4.0)
Requires-Dist: platipy (>=0.5.0)
Requires-Dist: pydicom (>=2.1.2)
Requires-Dist: pyorthanc (>=1.11.2)
Requires-Dist: pyradiomics (>=3.0.1)
Requires-Dist: scikit-learn (>=1.2.2,<2.0.0)
Requires-Dist: seaborn (>=0.12.0,<0.13.0)
Requires-Dist: tqdm (>=4.55.1,<5.0.0)
